mmar_mimpl/__init__.py
mmar_mimpl/models_resources.py
mmar_mimpl/models_settings.py
mmar_mimpl/parallel_map_ext.py
mmar_mimpl/py.typed
mmar_mimpl/validators_load_pydantic_model.py
mmar_mimpl-1.0.2.dist-info/licenses/LICENSE
mmar_mimpl-1.0.2.dist-info/WHEEL
mmar_mimpl-1.0.2.dist-info/METADATA
mmar_mimpl-1.0.2.dist-info/RECORD
