Metadata-Version: 2.4
Name: mmar-mimpl
Version: 1.0.2
Summary: MMAR Maestro Implementation
Keywords: 
Author: tagin
Author-email: tagin <tagin@airi.net>
License-Expression: MIT
License-File: LICENSE
Classifier: Development Status :: 4 - Beta
Classifier: Intended Audience :: Developers
Classifier: Programming Language :: Python
Classifier: Programming Language :: Python :: 3
Classifier: Programming Language :: Python :: 3 :: Only
Classifier: Programming Language :: Python :: 3.12
Classifier: Programming Language :: Python :: 3.13
Classifier: Programming Language :: Python :: 3.14
Classifier: Topic :: Documentation
Classifier: Topic :: Software Development
Classifier: Topic :: Utilities
Classifier: Typing :: Typed
Requires-Dist: pydantic~=2.12.5
Requires-Dist: pydantic-settings~=2.12.0
Requires-Dist: loguru~=0.7.3
Requires-Dist: mmar-ptag~=1.0.18
Requires-Python: >=3.12
